bgpstream_website_collector/__init__.py
bgpstream_website_collector/__main__.py
bgpstream_website_collector/bgpstream_website_collector.py
bgpstream_website_collector/front_page_info.py
bgpstream_website_collector/py.typed
bgpstream_website_collector/utils.py
bgpstream_website_collector/rows/__init__.py
bgpstream_website_collector/rows/hijack_row.py
bgpstream_website_collector/rows/leak_row.py
bgpstream_website_collector/rows/outage_row.py
bgpstream_website_collector/rows/row.py
bgpstream_website_collector/tests/__init__.py
bgpstream_website_collector/tests/test.py
bgpstream_website_collector-1.1.2.dist-info/LICENSE.txt
bgpstream_website_collector-1.1.2.dist-info/METADATA
bgpstream_website_collector-1.1.2.dist-info/WHEEL
bgpstream_website_collector-1.1.2.dist-info/entry_points.txt
bgpstream_website_collector-1.1.2.dist-info/top_level.txt
bgpstream_website_collector-1.1.2.dist-info/RECORD
