Metadata-Version: 2.1
Name: bgpstream-website-collector
Version: 1.1.2
Summary: Downloads BGPStream info solely for research purposes
Author: Tony Zheng
Author-email: Justin Furuness <jfuruness@gmail.com>
License: Copyright 2020, 2021 Justin Furuness
Project-URL: homepage, https://github.com/jfuruness/bgpstream_website_collector.git
Keywords: Furuness,BGP,Hijack,Outage,Leak,BGPStream,Peers,Customers,Providers,BGPStream.com
Classifier: Environment :: Console
Classifier: Intended Audience :: Developers
Classifier: License :: OSI Approved :: BSD License
Classifier: Operating System :: POSIX :: Linux
Classifier: Programming Language :: Python :: 3
Requires-Python: >=3.10
License-File: LICENSE.txt
Requires-Dist: beautifulsoup4 ==4.12.2
Requires-Dist: tqdm ==4.66.1
Requires-Dist: requests ==2.31.0
Requires-Dist: requests-cache ==1.1.1
Provides-Extra: test
Requires-Dist: types-beautifulsoup4 ~=4.12.0 ; extra == 'test'
Requires-Dist: types-requests ~=2.31.0 ; extra == 'test'
Requires-Dist: black ==23.7.0 ; extra == 'test'
Requires-Dist: pre-commit ==3.3.3 ; extra == 'test'
Requires-Dist: types-requests ==2.31.0 ; extra == 'test'
Requires-Dist: types-PyYAML ==6.0.11 ; extra == 'test'
Requires-Dist: mypy ==0.982 ; extra == 'test'
Requires-Dist: flake8 ==4.0.1 ; extra == 'test'
Requires-Dist: tox ==4.6.3 ; extra == 'test'
Requires-Dist: pytest-xdist ==2.5.0 ; extra == 'test'
Requires-Dist: ruff ==0.0.275 ; extra == 'test'
